{
    "id": "951558167",
    "name": "ORINEO BVBA",
    "children": [
        {
            "id": "935292334",
            "name": "REFRESCO GERBER UK LIMITED",
            "children": []
        },
        {
            "id": "992622050",
            "name": "NOVA-INSTITUT FUR POLITISCHE UND OKOLOGISCHE INNOVATION GMBH",
            "children": []
        },
        {
            "id": "986528219",
            "name": "BIO BASE EUROPE PILOT PLANT VZW",
            "children": []
        },
        {
            "id": "999981634",
            "name": "WAGENINGEN UNIVERSITY",
            "children": []
        },
        {
            "id": "995172083",
            "name": "KONINKLIJKE COOPERATIE COSUN UA",
            "children": []
        },
        {
            "id": "999547365",
            "name": "STICHTING WAGENINGEN RESEARCH",
            "children": []
        }
    ]
}