{
    "id": "997478064",
    "name": "DASEL SL",
    "children": [
        {
            "id": "954718427",
            "name": "C.R.E.A.T.E. CONSORZIO DI RICERCA PER L'ENERGIA L AUTOMAZIONE E LE TECNOLOGIE DELL'ELETTROMAGNETISMO",
            "children": []
        },
        {
            "id": "998189850",
            "name": "FUNDACION ANDALUZA PARA EL DESARROLLO AEROESPACIAL",
            "children": []
        },
        {
            "id": "999844670",
            "name": "OULUN YLIOPISTO",
            "children": []
        },
        {
            "id": "997172126",
            "name": "TOTAL S.A.",
            "children": []
        },
        {
            "id": "992244041",
            "name": "GE INSPECTION ROBOTICS AG",
            "children": []
        },
        {
            "id": "912350379",
            "name": "CHEVRON ORONITE SAS",
            "children": []
        },
        {
            "id": "999862518",
            "name": "UNIVERSIDAD DE SEVILLA",
            "children": []
        }
    ]
}