{
    "id": "998669806",
    "name": "FUNDACAO EUROCEAN",
    "children": [
        {
            "id": "999986193",
            "name": "UNIVERSITE PIERRE ET MARIE CURIE - PARIS 6",
            "children": []
        },
        {
            "id": "996698669",
            "name": "Europas Maritime Udviklingscenter",
            "children": []
        },
        {
            "id": "950397271",
            "name": "EUROGOOS",
            "children": []
        },
        {
            "id": "952856803",
            "name": "SEASCAPE CONSULTANTS LTD",
            "children": []
        },
        {
            "id": "997625504",
            "name": "AquaTT UETP Ltd",
            "children": []
        },
        {
            "id": "999980470",
            "name": "FORSCHUNGSZENTRUM JULICH GMBH",
            "children": []
        },
        {
            "id": "972130024",
            "name": "Unitatea Executiva pentru Finantarea Invatamantului Superior, a Cercetarii, Dezvoltarii si Inovarii",
            "children": []
        },
        {
            "id": "974644458",
            "name": "CONSORCIO PARA EL DISENO, CONSTRUCCION, EQUIPAMIENTO Y EXPLOTACION DE LA PLATAFORMA OCEANICA DE CANARIAS",
            "children": []
        },
        {
            "id": "998895234",
            "name": "European Council for Maritime Applied R&D Association",
            "children": []
        },
        {
            "id": "952690448",
            "name": "SMARTBAY IRELAND",
            "children": []
        },
        {
            "id": "991809966",
            "name": "CENTRO TECNOLOGICO DEL MAR - FUNDACION CETMAR",
            "children": []
        },
        {
            "id": "997989545",
            "name": "SOCIETE D'EXPLOITATION DU CENTRE NATIONAL DE LA MER",
            "children": []
        },
        {
            "id": "951273375",
            "name": "AQUATERA LIMITED",
            "children": []
        },
        {
            "id": "994679905",
            "name": "MARINE SOUTH EAST",
            "children": []
        },
        {
            "id": "999904713",
            "name": "THE SECRETARY OF STATE FOR ENVIRONMENT, FOOD AND RURAL AFFAIRS",
            "children": []
        },
        {
            "id": "997384750",
            "name": "EUROPEAN AQUACULTURE SOCIETY",
            "children": []
        },
        {
            "id": "986285719",
            "name": "BORD IASCAIGH MHARA",
            "children": []
        },
        {
            "id": "985318338",
            "name": "SOCIEDAD PARA EL FOMENTO DE LA INNOVACION TECNOLOGICA S.L. - INNOVATEC",
            "children": []
        },
        {
            "id": "999990655",
            "name": "DANMARKS TEKNISKE UNIVERSITET",
            "children": []
        },
        {
            "id": "957934462",
            "name": "PANAGIOTIS CHRISTOFILOGIANNIS - IOANA TAVLA",
            "children": []
        },
        {
            "id": "999599939",
            "name": "VLAAMS INSTITUUT VOOR DE ZEE VZW",
            "children": []
        },
        {
            "id": "999977851",
            "name": "NORGES TEKNISK-NATURVITENSKAPELIGE UNIVERSITET NTNU",
            "children": []
        },
        {
            "id": "998073450",
            "name": "CENTER OF MARITIME TECHNOLOGIES EV",
            "children": []
        },
        {
            "id": "999989200",
            "name": "NATURAL ENVIRONMENT RESEARCH COUNCIL",
            "children": []
        },
        {
            "id": "999513221",
            "name": "SINTEF ENERGI AS",
            "children": []
        },
        {
            "id": "999864555",
            "name": "THE UNIVERSITY OF EXETER",
            "children": []
        },
        {
            "id": "941752728",
            "name": "FUNDACION INSTITUTO DE HIDRAULICA AMBIENTAL DE CANTABRIA",
            "children": []
        },
        {
            "id": "999978045",
            "name": "NATIONAL UNIVERSITY OF IRELAND GALWAY",
            "children": []
        },
        {
            "id": "972504347",
            "name": "FUNDACION CENTRO TECNOLOGICO DE COMPONENTES",
            "children": []
        },
        {
            "id": "999604110",
            "name": "FUNDACION TECNALIA RESEARCH & INNOVATION",
            "children": []
        },
        {
            "id": "999895789",
            "name": "UNIVERSITA DEGLI STUDI DI FIRENZE",
            "children": []
        },
        {
            "id": "999509050",
            "name": "ECOLE CENTRALE DE NANTES",
            "children": []
        },
        {
            "id": "999985029",
            "name": "UPPSALA UNIVERSITET",
            "children": []
        },
        {
            "id": "999854661",
            "name": "UNIVERSITY OF PLYMOUTH",
            "children": []
        },
        {
            "id": "999809071",
            "name": "UNIVERSITY OF LIMERICK",
            "children": []
        },
        {
            "id": "937212643",
            "name": "BISCAY MARINE ENERGY PLATFORM SA",
            "children": []
        },
        {
            "id": "999992013",
            "name": "THE QUEEN'S UNIVERSITY OF BELFAST",
            "children": []
        },
        {
            "id": "999979500",
            "name": "CONSIGLIO NAZIONALE DELLE RICERCHE",
            "children": []
        },
        {
            "id": "999543485",
            "name": "WAVEC/OFFSHORE RENEWABLES - CENTRO DE ENERGIA OFFSHORE ASSOCIACAO",
            "children": []
        },
        {
            "id": "999493239",
            "name": "THE EUROPEAN MARINE ENERGY CENTRE LIMITED",
            "children": []
        },
        {
            "id": "998073644",
            "name": "STICHTING MARITIEM RESEARCH INSTITUUT NEDERLAND",
            "children": []
        },
        {
            "id": "999630300",
            "name": "INSTITUT FRANCAIS DE RECHERCHE POUR L'EXPLOITATION DE LA MER",
            "children": []
        },
        {
            "id": "998073159",
            "name": "SSPA SWEDEN AB.",
            "children": []
        },
        {
            "id": "998811620",
            "name": "OFFSHORE RENEWABLE ENERGY CATAPULT",
            "children": []
        },
        {
            "id": "999745342",
            "name": "FUNDACION CENER-CIEMAT",
            "children": []
        },
        {
            "id": "998621694",
            "name": "MARIENE INFORMATIE SERVICE MARIS BV",
            "children": []
        },
        {
            "id": "941593842",
            "name": "FLOWAVE TT LIMITED",
            "children": []
        },
        {
            "id": "919761761",
            "name": "OCEANIDE",
            "children": []
        },
        {
            "id": "999985223",
            "name": "UNIVERSITY OF SURREY",
            "children": []
        },
        {
            "id": "999975717",
            "name": "UNIVERSITY COLLEGE CORK -  NATIONAL UNIVERSITY OF IRELAND, CORK",
            "children": []
        },
        {
            "id": "999904034",
            "name": "AALBORG UNIVERSITET",
            "children": []
        },
        {
            "id": "999974941",
            "name": "THE UNIVERSITY OF EDINBURGH",
            "children": []
        },
        {
            "id": "997911363",
            "name": "ENTE VASCO DE LA ENERGIA",
            "children": []
        },
        {
            "id": "999645820",
            "name": "CSC-TIETEEN TIETOTEKNIIKAN KESKUS OY",
            "children": []
        },
        {
            "id": "999981828",
            "name": "GOTTFRIED WILHELM LEIBNIZ UNIVERSITAET HANNOVER",
            "children": []
        },
        {
            "id": "999974068",
            "name": "UNIVERSITY OF STRATHCLYDE",
            "children": []
        },
        {
            "id": "999548432",
            "name": "HAVFORSKNINGSINSTITUTTET",
            "children": []
        },
        {
            "id": "999997736",
            "name": "AARHUS UNIVERSITET",
            "children": []
        },
        {
            "id": "999889387",
            "name": "INSTITUTE OF REMOTE SENSING AND DIGITAL EARTH - CHINESE ACADEMY OF SCIENCE",
            "children": []
        },
        {
            "id": "999917614",
            "name": "UNIWERSYTET SLASKI",
            "children": []
        },
        {
            "id": "999994535",
            "name": "HELSINGIN YLIOPISTO",
            "children": []
        },
        {
            "id": "999976881",
            "name": "THE UNIVERSITY OF SHEFFIELD",
            "children": []
        },
        {
            "id": "912924328",
            "name": "UNIVERSITAET HAMBURG",
            "children": []
        },
        {
            "id": "999621570",
            "name": "NORUT NORTHERN RESEARCH INSTITUTE AS",
            "children": []
        },
        {
            "id": "888898380",
            "name": "MAX-PLANCK-GESELLSCHAFT ZUR FORDERUNG DER WISSENSCHAFTEN EV",
            "children": []
        },
        {
            "id": "998225449",
            "name": "University Centre in Svalbard",
            "children": []
        },
        {
            "id": "999901415",
            "name": "NATIONAL UNIVERSITY OF IRELAND MAYNOOTH",
            "children": []
        },
        {
            "id": "997711252",
            "name": "ALL-RUSSIAN RESEARCH INSTITUTE OF HYDROMETEOROLOGICAL INFORMATION-WORLD DATA CENTRE",
            "children": []
        },
        {
            "id": "998049685",
            "name": "Scientific foundation Nansen International Environmental and Remote Sensing Centre",
            "children": []
        },
        {
            "id": "999929060",
            "name": "DNV GL AS",
            "children": []
        },
        {
            "id": "999507983",
            "name": "SVERIGES METEOROLOGISKA OCH HYDROLOGISKA INSTITUT",
            "children": []
        },
        {
            "id": "999497507",
            "name": "ALFRED-WEGENER-INSTITUT HELMHOLTZ-ZENTRUM FUR POLAR- UND MEERESFORSCHUNG",
            "children": []
        },
        {
            "id": "999994341",
            "name": "HELMHOLTZ ZENTRUM POTSDAM DEUTSCHESGEOFORSCHUNGSZENTRUM GFZ",
            "children": []
        },
        {
            "id": "999981246",
            "name": "ASSOCIATION POUR LA RECHERCHE ET LE DEVELOPPEMENT DES METHODES ET PROCESSUS INDUSTRIELS",
            "children": []
        },
        {
            "id": "999987454",
            "name": "UNIVERSITAET BREMEN",
            "children": []
        },
        {
            "id": "999488971",
            "name": "INSTYTUT OCEANOLOGII POLSKIEJ AKADEMII NAUK",
            "children": []
        },
        {
            "id": "999477913",
            "name": "STIFTELSEN NANSEN SENTER FOR MILJOOG FJERNMALING",
            "children": []
        },
        {
            "id": "999459677",
            "name": "Geological Survey of Denmark and Greenland",
            "children": []
        },
        {
            "id": "999467340",
            "name": "THE REGENTS OF THE UNIVERSITY OF CALIFORNIA",
            "children": []
        },
        {
            "id": "999591306",
            "name": "ILMATIETEEN LAITOS",
            "children": []
        },
        {
            "id": "997826585",
            "name": "NORSK INSTITUTT FOR VANNFORSKNING",
            "children": []
        },
        {
            "id": "999732829",
            "name": "TERRADUE SRL",
            "children": []
        },
        {
            "id": "998082180",
            "name": "UNIVERSITE LAVAL",
            "children": []
        },
        {
            "id": "998297908",
            "name": "GRONLANDS NATURINSTITUT",
            "children": []
        },
        {
            "id": "998794063",
            "name": "WOODS HOLE OCEANOGRAPHIC INSTITUTION",
            "children": []
        },
        {
            "id": "999923337",
            "name": "THE OPEN UNIVERSITY",
            "children": []
        },
        {
            "id": "986361476",
            "name": "NORDISK FOND FOR MILJØ OG UDVIKLING",
            "children": []
        },
        {
            "id": "999997930",
            "name": "CENTRE NATIONAL DE LA RECHERCHE SCIENTIFIQUE CNRS",
            "children": []
        },
        {
            "id": "999974844",
            "name": "UNIVERSIDAD POLITECNICA DE MADRID",
            "children": []
        },
        {
            "id": "999974456",
            "name": "UNIVERSITETET I BERGEN",
            "children": []
        },
        {
            "id": "999655520",
            "name": "BARCELONA SUPERCOMPUTING CENTER - CENTRO NACIONAL DE SUPERCOMPUTACION",
            "children": []
        },
        {
            "id": "999885022",
            "name": "STOCKHOLMS UNIVERSITET",
            "children": []
        },
        {
            "id": "996625337",
            "name": "Instytut Geofizyki Polskiej Akademii Nauk",
            "children": []
        },
        {
            "id": "999473160",
            "name": "Asociacion - Centro de Investigacion Cooperativa en Nanociencias - CIC NANOGUNE",
            "children": []
        },
        {
            "id": "999514191",
            "name": "AGENZIA PER LA PROMOZIONE DELLA RICERCA EUROPEA",
            "children": []
        },
        {
            "id": "968653641",
            "name": "RESEAU OCEAN MONDIAL AISBL",
            "children": []
        },
        {
            "id": "997905349",
            "name": "Istituto Superiore per la Protezione e la Ricerca Ambientale",
            "children": []
        },
        {
            "id": "999936432",
            "name": "SIHTASUTUS TEADUSKESKUS AHHAA",
            "children": []
        },
        {
            "id": "998391222",
            "name": "ISTANBUL UNIVERSITESI",
            "children": []
        },
        {
            "id": "984004376",
            "name": "XPRO CONSULTING LIMITED",
            "children": []
        },
        {
            "id": "968769071",
            "name": "ORGANIZATIA ECOLOGISTA NEGUVERNAMENTALA MARE NOSTRUM",
            "children": []
        },
        {
            "id": "991509945",
            "name": "CYPRUS NEUROSCIENCE AND TECHNOLOGY INSTITUTE",
            "children": []
        }
    ]
}