{
    "id": "998894555",
    "name": "CONSORCIO REGIONAL DE TRANSPORTES DE MADRID",
    "children": [
        {
            "id": "998894458",
            "name": "Verband Deutscher Verkehrsunternehmen",
            "children": []
        },
        {
            "id": "999472093",
            "name": "HUEBNER GUMMI- UND KUNSTSTOFF GMBH",
            "children": []
        },
        {
            "id": "996820404",
            "name": "PLUSERVICE SRL",
            "children": []
        },
        {
            "id": "998140671",
            "name": "VASTTRAFIK AB",
            "children": []
        },
        {
            "id": "999482666",
            "name": "RUPPRECHT CONSULT-FORSCHUNG & BERATUNG GMBH",
            "children": []
        },
        {
            "id": "998554279",
            "name": "Hogia Public Transport Systems AB",
            "children": []
        },
        {
            "id": "986056411",
            "name": "COMPANIA DEL TRANVIA DE SAN SEBASTIAN SA - CTSS",
            "children": []
        },
        {
            "id": "932760440",
            "name": "Teknologian tutkimuskeskus VTT Oy",
            "children": []
        },
        {
            "id": "999984059",
            "name": "FRAUNHOFER GESELLSCHAFT ZUR FOERDERUNG DER ANGEWANDTEN FORSCHUNG E.V.",
            "children": []
        },
        {
            "id": "998139410",
            "name": "SYNDICAT MIXTE DES TRANSPORTS POURLE RHONE ET L AGGLOMERATION LYONNAISE",
            "children": []
        },
        {
            "id": "999992401",
            "name": "COMMISSARIAT A L ENERGIE ATOMIQUE ET AUX ENERGIES ALTERNATIVES",
            "children": []
        },
        {
            "id": "998087224",
            "name": "INEO SYSTRANS",
            "children": []
        },
        {
            "id": "999746409",
            "name": "TIS PT, CONSULTORES EM TRANSPORTES, INOVACAO E SISTEMAS, SA",
            "children": []
        },
        {
            "id": "998379970",
            "name": "IVECO FRANCE SA",
            "children": []
        },
        {
            "id": "999951467",
            "name": "RINA CONSULTING SPA",
            "children": []
        },
        {
            "id": "999928381",
            "name": "POLIS - PROMOTION OF OPERATIONAL LINKS WITH INTEGRATED SERVICES, ASSOCIATION INTERNATIONALE",
            "children": []
        },
        {
            "id": "937030574",
            "name": "TRAPEZE ITS UK LTD",
            "children": []
        },
        {
            "id": "932761313",
            "name": "DIGIGROUP INFORMATICA SRL",
            "children": []
        },
        {
            "id": "996424062",
            "name": "Volvo Bus Corporation",
            "children": []
        },
        {
            "id": "999526413",
            "name": "ASSTRA - ASSOCIAZIONE TRASPORTI",
            "children": []
        },
        {
            "id": "932679348",
            "name": "START ROMAGNA SPA",
            "children": []
        },
        {
            "id": "998397333",
            "name": "TEKIA CONSULTORES TECNOLÓGICOS S.L.",
            "children": []
        },
        {
            "id": "998380067",
            "name": "UNION DES TRANSPORTS PUBLICS - (U.T.P)",
            "children": []
        },
        {
            "id": "999945647",
            "name": "UNION INTERNATIONALE DES TRANSPORTS PUBLICS",
            "children": []
        },
        {
            "id": "998181702",
            "name": "EVOBUS GMBH",
            "children": []
        },
        {
            "id": "999755721",
            "name": "FIT CONSULTING SRL",
            "children": []
        },
        {
            "id": "950289601",
            "name": "DIGIMOBEE SAS",
            "children": []
        },
        {
            "id": "942615737",
            "name": "KEOLIS",
            "children": []
        },
        {
            "id": "998645944",
            "name": "Pilotfish Networks AB",
            "children": []
        },
        {
            "id": "932953567",
            "name": "MEL SYSTEMS SRL",
            "children": []
        },
        {
            "id": "999707221",
            "name": "REGIE AUTONOME DES TRANSPORTS PARISIENS",
            "children": []
        },
        {
            "id": "999430189",
            "name": "TRANSPORT FOR LONDON*TFL",
            "children": []
        },
        {
            "id": "937596375",
            "name": "STUTTGARTER STRASSENBAHNEN AG",
            "children": []
        },
        {
            "id": "958594256",
            "name": "ACTIA AUTOMOTIVE",
            "children": []
        },
        {
            "id": "999974844",
            "name": "UNIVERSIDAD POLITECNICA DE MADRID",
            "children": []
        },
        {
            "id": "956704308",
            "name": "TRANSPORTS DE BARCELONA SA",
            "children": []
        },
        {
            "id": "999605662",
            "name": "ASOCIACION CENTRO TECNOLOGICO CEIT-IK4",
            "children": []
        },
        {
            "id": "999987745",
            "name": "UNIVERSITA DEGLI STUDI DI ROMA LA SAPIENZA",
            "children": []
        },
        {
            "id": "950600680",
            "name": "IRIZAR S COOP",
            "children": []
        },
        {
            "id": "998507137",
            "name": "Innovative Informatikanwendungen in Transport-, Verkehrs- und Leitsystemen GmbH",
            "children": []
        },
        {
            "id": "999980373",
            "name": "CHALMERS TEKNISKA HOEGSKOLA AB",
            "children": []
        },
        {
            "id": "999639709",
            "name": "FUNDACION INSTITUTO GERONTOLOGICO MATIA - INGEMA",
            "children": []
        },
        {
            "id": "888897696",
            "name": "LINKOPINGS UNIVERSITET",
            "children": []
        },
        {
            "id": "941027750",
            "name": "SHEFFCARE LIMITED",
            "children": []
        },
        {
            "id": "941625949",
            "name": "DOKTOR 24 ZDRAVSTVENE IN TELEMEDICINSKE STORITVE DOO",
            "children": []
        },
        {
            "id": "998802502",
            "name": "ETHNIKO KENTRO EREVNAS KAI TECHNOLOGIKIS ANAPTYXIS",
            "children": []
        },
        {
            "id": "985402146",
            "name": "VIRTUALWARE 2007 SA",
            "children": []
        },
        {
            "id": "954192493",
            "name": "STICHTING TRIVIUM MEULENBELT GROEP",
            "children": []
        },
        {
            "id": "999976881",
            "name": "THE UNIVERSITY OF SHEFFIELD",
            "children": []
        },
        {
            "id": "999892588",
            "name": "DUBLIN CITY UNIVERSITY",
            "children": []
        },
        {
            "id": "999971837",
            "name": "INSTITUT JOZEF STEFAN",
            "children": []
        },
        {
            "id": "999473936",
            "name": "ROESSINGH RESEARCH AND DEVELOPMENT BV",
            "children": []
        },
        {
            "id": "985888407",
            "name": "MLS MULTIMEDIA AE",
            "children": []
        },
        {
            "id": "945019203",
            "name": "GENIKO NOSOKOMEIO THESSALONIKIS G.PAPANIKOLAOU",
            "children": []
        },
        {
            "id": "940610359",
            "name": "VEREIN ZUR FOERDERUNG ASSISTIERENDER TECHNOLOGIE IN EUROPA",
            "children": []
        },
        {
            "id": "996421540",
            "name": "BYTE COMPUTER ANONYMI VIOMICHANIKIEMPORIKI ETAIREIA",
            "children": []
        },
        {
            "id": "999651640",
            "name": "VASTRA GOTALANDS LANS LANDSTING",
            "children": []
        },
        {
            "id": "949857563",
            "name": "OPEN EVIDENCE",
            "children": []
        },
        {
            "id": "996477121",
            "name": "INTERNATIONALES INFORMATIONSZENTRUM FUR TERMINOLOGIE",
            "children": []
        },
        {
            "id": "984516342",
            "name": "EMPRESA MUNICIPAL DE TRANSPORTES DE MADRID SA",
            "children": []
        },
        {
            "id": "925656936",
            "name": "MOBILITY MOTORS SWEDEN AB",
            "children": []
        },
        {
            "id": "993966082",
            "name": "CITY OF TURKU",
            "children": []
        },
        {
            "id": "926126804",
            "name": "GREEN CITY PROJEKT GMBH",
            "children": []
        },
        {
            "id": "925414533",
            "name": "WESTERN SYSTEMS OY",
            "children": []
        },
        {
            "id": "925413854",
            "name": "TURUN KAUPUNKILIIKENNE OY",
            "children": []
        },
        {
            "id": "999990946",
            "name": "KUNGLIGA TEKNISKA HOEGSKOLAN",
            "children": []
        },
        {
            "id": "991015924",
            "name": "OBSHTINA RUSE",
            "children": []
        },
        {
            "id": "925983923",
            "name": "FLEXIDRIVE SVERIGE AB",
            "children": []
        },
        {
            "id": "925831245",
            "name": "UBIGO INNOVATION AB",
            "children": []
        },
        {
            "id": "925494655",
            "name": "DOMAGKPARK GENOSSENSCHAFT EG",
            "children": []
        },
        {
            "id": "999977463",
            "name": "TECHNISCHE UNIVERSITAET MUENCHEN",
            "children": []
        },
        {
            "id": "950594763",
            "name": "CYKELKONSULTERNA SVERIGE AB",
            "children": []
        },
        {
            "id": "932881011",
            "name": "GREEN CITY EV",
            "children": []
        },
        {
            "id": "966644480",
            "name": "CLUB SUSTAINABLE DEVELOPMENT OF CIVIL SOCIETY ASSOCIATION",
            "children": []
        },
        {
            "id": "935852994",
            "name": "FM LOGISTIC CORPORATE",
            "children": []
        },
        {
            "id": "948193431",
            "name": "TURUN AMMATTIKORKEAKOULU OY",
            "children": []
        },
        {
            "id": "997513178",
            "name": "AYUNTAMIENTO DE MADRID",
            "children": []
        },
        {
            "id": "944829083",
            "name": "GOMORE APS",
            "children": []
        },
        {
            "id": "996559183",
            "name": "STOCKHOLMS STAD",
            "children": []
        },
        {
            "id": "991738089",
            "name": "AVIA INGENIERIA Y DISEGNO",
            "children": []
        },
        {
            "id": "986044480",
            "name": "GRUPO DE ESTUDIOS Y ALTERNATIVAS 21SL - GEA 21",
            "children": []
        },
        {
            "id": "998341364",
            "name": "ICLEI EUROPEAN SECRETARIAT GMBH (ICLEI EUROPASEKRETARIAT GMBH)*",
            "children": []
        },
        {
            "id": "950866460",
            "name": "VARSINAIS-SUOMEN LIITTO",
            "children": []
        },
        {
            "id": "925477680",
            "name": "GASUM BIOVAKKA OY",
            "children": []
        },
        {
            "id": "997625601",
            "name": "LANDESHAUPTSTADT MUENCHEN",
            "children": []
        },
        {
            "id": "999751744",
            "name": "ATHENS TECHNOLOGY CENTER ANONYMI BIOMICHANIKI EMPORIKI KAI TECHNIKI ETAIREIA EFARMOGON YPSILIS TECHNOLOGIAS",
            "children": []
        },
        {
            "id": "999624480",
            "name": "BIRMINGHAM CITY COUNCIL",
            "children": []
        },
        {
            "id": "941559892",
            "name": "FUTURE CITIES LAB LTD",
            "children": []
        },
        {
            "id": "991350089",
            "name": "DIMOS ATHINAION EPICHEIRISI MICHANOGRAFISIS",
            "children": []
        },
        {
            "id": "960216387",
            "name": "CITTA DI LECCE*COMUNE DI LECCE",
            "children": []
        },
        {
            "id": "999893752",
            "name": "UNIVERSITA DEGLI STUDI DI PAVIA",
            "children": []
        },
        {
            "id": "984514305",
            "name": "GEOMOBILE GMBH",
            "children": []
        },
        {
            "id": "999879881",
            "name": "POLITECNICO DI MILANO",
            "children": []
        },
        {
            "id": "975084450",
            "name": "PREDUZECE ZA INFORMACIONE TEHNOLOGIJE I ELEKTRONSKO TRGOVANJE BELIT DOO",
            "children": []
        },
        {
            "id": "999975620",
            "name": "UNIVERSITY COLLEGE LONDON",
            "children": []
        },
        {
            "id": "999876971",
            "name": "UNIVERSIDAD DE LA IGLESIA DE DEUSTO ENTIDAD RELIGIOSA",
            "children": []
        },
        {
            "id": "999997930",
            "name": "CENTRE NATIONAL DE LA RECHERCHE SCIENTIFIQUE CNRS",
            "children": []
        },
        {
            "id": "936166983",
            "name": "MULTIMED ENGINEERS SRL",
            "children": []
        },
        {
            "id": "999863585",
            "name": "UNIVERSITA DEL SALENTO",
            "children": []
        }
    ]
}