{
    "orgId": "927161115",
    "orgName": "LADIMO OY",
    "orgCountry": "Finland",
    "orgAddr": "SPEKTRI BUSINESS PARK METSANNEIDONKUJA 6 02130 ESPOO",
    "orgGeoloc": [
        24.6603626,
        60.2241869
    ],
    "orgLat": 60.2241869,
    "orgLng": 24.6603626,
    "orgProjects": {
        "213626": {
            "Acronym": "SmartEye",
            "rcn": "213626",
            "ecContrib": 50000,
            "projectTotalCost": 71429,
            "projectEuContrib": 50000
        }
    },
    "orgRelCompanies": {},
    "orgSector": "/PRC",
    "orgEcContr": 50000
}