{
    "orgId": "943112571",
    "orgName": "COMMUNICATION & INFORMATION TECHNOLOGIES EXPERTS ANONYMOS ETAIREIA SYMVOULEFTIKON KAI ANAPTYXIAKON YPIRESION",
    "orgCountry": "Greece",
    "orgAddr": "ETHNIKIS ANTISTASEOS 178 16122 KAISARIANI",
    "orgGeoloc": [
        23.7725995,
        37.9702121
    ],
    "orgLat": 37.9702121,
    "orgLng": 23.7725995,
    "orgProjects": {
        "196704": {
            "Acronym": "EarthServer-2",
            "rcn": "196704",
            "ecContrib": 325750,
            "projectTotalCost": 2839744,
            "projectEuContrib": 2839743
        },
        "198301": {
            "Acronym": "BlueBRIDGE",
            "rcn": "198301",
            "ecContrib": 212688,
            "projectTotalCost": 5295754,
            "projectEuContrib": 5295754
        }
    },
    "orgRelCompanies": {
        "999484024": "PLYMOUTH MARINE LABORATORY",
        "972294439": "METEOROLOGICAL AND ENVIRONMENTAL EARTH OBSERVATION SRL",
        "999897147": "JACOBS UNIVERSITY BREMEN GGMBH",
        "972352251": "RASDAMAN GMBH",
        "999916741": "EUROPEAN CENTRE FOR MEDIUM-RANGE WEATHER FORECASTS",
        "999849132": "THE AUSTRALIAN NATIONAL UNIVERSITY",
        "999608281": "FOOD AND AGRICULTURE ORGANIZATION OF THE UNITED NATIONS FAO",
        "971632414": "OLOKLIROMENA PLIROFORIAKA SISTIMATA",
        "999643007": "ETHNIKO KAI KAPODISTRIAKO PANEPISTIMIO ATHINON",
        "999995893": "FOUNDATION FOR RESEARCH AND TECHNOLOGY HELLAS",
        "941833626": "STIFTELSEN GRID ARENDAL",
        "994505984": "ASSOCIATION POLE MER BRETAGNE",
        "999979500": "CONSIGLIO NAZIONALE DELLE RICERCHE",
        "998142126": "COLLECTE LOCALISATION SATELLITES SA",
        "999687724": "TRUST-IT SERVICES LIMITED",
        "999960488": "ENGINEERING - INGEGNERIA INFORMATICA SPA",
        "999593828": "GEIE ERCIM",
        "999513803": "INSTITUT DE RECHERCHE POUR LE DEVELOPPEMENT"
    },
    "orgSector": "/PRC",
    "orgEcContr": 538438
}